grook.py
grook-0.1.2.dist-info/METADATA
grook-0.1.2.dist-info/WHEEL
grook-0.1.2.dist-info/entry_points.txt
grook-0.1.2.dist-info/RECORD
