Metadata-Version: 2.4
Name: grook
Version: 0.1.2
Summary: Simple unofficial client for free access to Grok AI models
Author-email: AKM Korishee Apurbo <bandinvisible8@gmail.com>
License: MIT
Keywords: ai,chatbot,grok,unofficial,xai
Classifier: License :: OSI Approved :: MIT License
Classifier: Programming Language :: Python :: 3
Classifier: Topic :: Scientific/Engineering :: Artificial Intelligence
Requires-Python: >=3.8
Requires-Dist: beautifulsoup4
Requires-Dist: coincurve
Requires-Dist: curl-cffi>=0.7.0
Requires-Dist: platformdirs
Provides-Extra: dev
Requires-Dist: pytest; extra == 'dev'
